offlineslides/__init__.py
offlineslides/offlineslides.py
offlineslides-0.2.0.dist-info/LICENSE
offlineslides-0.2.0.dist-info/METADATA
offlineslides-0.2.0.dist-info/WHEEL
offlineslides-0.2.0.dist-info/entry_points.txt
offlineslides-0.2.0.dist-info/top_level.txt
offlineslides-0.2.0.dist-info/RECORD
