Metadata-Version: 2.1
Name: offlineslides
Version: 0.2.0
Summary: Program to make a jupyter notebook into offline reveal.js slideshow
Home-page: https://github.com/alexisfcote/offline_slides
Author: Alexis Fortin-Côté
License: UNKNOWN
Platform: UNKNOWN
Classifier: Programming Language :: Python :: 3
Classifier: License :: OSI Approved :: MIT License
Classifier: Operating System :: Microsoft :: Windows
Classifier: Operating System :: POSIX :: Linux
Classifier: Environment :: Console
Requires-Dist: nbconvert
Requires-Dist: requests
Requires-Dist: nbformat
